ssds/ArrayHeapPQ.py
ssds/__init__.py
ssds/abc/PriorityQueue.py
ssds/abc/__init__.py
ssds/reference/ReferencePQ.py
ssds/reference/__init__.py
tests/TestArrayHeapPQ.py
tests/__init__.py
ssds-0.1.1.dist-info/LICENSE
ssds-0.1.1.dist-info/METADATA
ssds-0.1.1.dist-info/WHEEL
ssds-0.1.1.dist-info/top_level.txt
ssds-0.1.1.dist-info/RECORD
