Metadata-Version: 2.1
Name: ssds
Version: 0.1.1
Summary: Some specialized data structures for Python.
Home-page: https://github.com/claytsay/ssds-python
Author: Clay Tsay
Author-email: 
License: UNKNOWN
Platform: UNKNOWN
Classifier: Programming Language :: Python :: 3
Classifier: License :: OSI Approved :: Apache Software License
Classifier: Operating System :: OS Independent
Requires-Python: >=3.6
